[{
    "name": "on a break",
    "counts": [
        [
            "RACHEL",
            2
        ],
        [
            "ROSS",
            10
        ],
        [
            "MONICA",
            0
        ],
        [
            "CHANDLER",
            0
        ],
        [
            "JOEY",
            1
        ],
        [
            "PHOEBE",
            2
        ]
    ]
}, {
    "name": "sorry",
    "counts": [
        [
            "RACHEL",
            295
        ],
        [
            "ROSS",
            220
        ],
        [
            "MONICA",
            179
        ],
        [
            "CHANDLER",
            144
        ],
        [
            "JOEY",
            159
        ],
        [
            "PHOEBE",
            203
        ]
    ]
}, {
    "name": "i, me, mine",
    "counts": [
        [
            "RACHEL",
            6106
        ],
        [
            "ROSS",
            5698
        ],
        [
            "MONICA",
            4573
        ],
        [
            "CHANDLER",
            4904
        ],
        [
            "JOEY",
            5133
        ],
        [
            "PHOEBE",
            4396
        ]
    ]
}, {
    "name": "ugly naked guy",
    "counts": [
        [
            "RACHEL",
            2
        ],
        [
            "ROSS",
            3
        ],
        [
            "MONICA",
            1
        ],
        [
            "CHANDLER",
            1
        ],
        [
            "JOEY",
            4
        ],
        [
            "PHOEBE",
            7
        ]
    ]
}, {
    "name": "how you doin",
    "counts": [
        [
            "RACHEL",
            4
        ],
        [
            "ROSS",
            1
        ],
        [
            "MONICA",
            1
        ],
        [
            "CHANDLER",
            0
        ],
        [
            "JOEY",
            22
        ],
        [
            "PHOEBE",
            0
        ]
    ]
}, {
    "name": "love",
    "counts": [
        [
            "RACHEL",
            183
        ],
        [
            "ROSS",
            144
        ],
        [
            "MONICA",
            173
        ],
        [
            "CHANDLER",
            142
        ],
        [
            "JOEY",
            97
        ],
        [
            "PHOEBE",
            137
        ]
    ]
}, {
    "name": "sex, date, kiss",
    "counts": [
        [
            "RACHEL",
            145
        ],
        [
            "ROSS",
            128
        ],
        [
            "MONICA",
            94
        ],
        [
            "CHANDLER",
            98
        ],
        [
            "JOEY",
            123
        ],
        [
            "PHOEBE",
            88
        ]
    ]
}, {
    "name": "ex, exes",
    "counts": [
        [
            "RACHEL",
            5
        ],
        [
            "ROSS",
            19
        ],
        [
            "MONICA",
            6
        ],
        [
            "CHANDLER",
            7
        ],
        [
            "JOEY",
            3
        ],
        [
            "PHOEBE",
            4
        ]
    ]
}, {
    "name": "baby, child, children, kid",
    "counts": [
        [
            "RACHEL",
            129
        ],
        [
            "ROSS",
            144
        ],
        [
            "MONICA",
            146
        ],
        [
            "CHANDLER",
            95
        ],
        [
            "JOEY",
            117
        ],
        [
            "PHOEBE",
            96
        ]
    ]
}, {
    "name": "coffee, coffeehouse",
    "counts": [
        [
            "RACHEL",
            33
        ],
        [
            "ROSS",
            36
        ],
        [
            "MONICA",
            16
        ],
        [
            "CHANDLER",
            27
        ],
        [
            "JOEY",
            22
        ],
        [
            "PHOEBE",
            24
        ]
    ]
}, {
    "name": "work, job, career",
    "counts": [
        [
            "RACHEL",
            163
        ],
        [
            "ROSS",
            123
        ],
        [
            "MONICA",
            166
        ],
        [
            "CHANDLER",
            137
        ],
        [
            "JOEY",
            119
        ],
        [
            "PHOEBE",
            91
        ]
    ]
}, {
    "name": "commitment, relationship, marriage, dating",
    "counts": [
        [
            "RACHEL",
            42
        ],
        [
            "ROSS",
            82
        ],
        [
            "MONICA",
            41
        ],
        [
            "CHANDLER",
            51
        ],
        [
            "JOEY",
            18
        ],
        [
            "PHOEBE",
            34
        ]
    ]
}, {
    "name": "parents, parent, mom, dad, mother, father",
    "counts": [
        [
            "RACHEL",
            117
        ],
        [
            "ROSS",
            189
        ],
        [
            "MONICA",
            184
        ],
        [
            "CHANDLER",
            107
        ],
        [
            "JOEY",
            89
        ],
        [
            "PHOEBE",
            169
        ]
    ]
}, {
    "name": "gay, lesbian",
    "counts": [
        [
            "RACHEL",
            13
        ],
        [
            "ROSS",
            32
        ],
        [
            "MONICA",
            9
        ],
        [
            "CHANDLER",
            18
        ],
        [
            "JOEY",
            21
        ],
        [
            "PHOEBE",
            16
        ]
    ]
}, {
    "name": "oh my god",
    "counts": [
        [
            "RACHEL",
            256
        ],
        [
            "ROSS",
            114
        ],
        [
            "MONICA",
            232
        ],
        [
            "CHANDLER",
            72
        ],
        [
            "JOEY",
            61
        ],
        [
            "PHOEBE",
            173
        ]
    ]
}, {
    "name": "uh",
    "counts": [
        [
            "RACHEL",
            335
        ],
        [
            "ROSS",
            747
        ],
        [
            "MONICA",
            161
        ],
        [
            "CHANDLER",
            310
        ],
        [
            "JOEY",
            502
        ],
        [
            "PHOEBE",
            164
        ]
    ]
}, {
    "name": "i dont know",
    "counts": [
        [
            "RACHEL",
            138
        ],
        [
            "ROSS",
            122
        ],
        [
            "MONICA",
            66
        ],
        [
            "CHANDLER",
            85
        ],
        [
            "JOEY",
            136
        ],
        [
            "PHOEBE",
            87
        ]
    ]
}, {
    "name": "rachel, rach",
    "counts": [
        [
            "RACHEL",
            76
        ],
        [
            "ROSS",
            390
        ],
        [
            "MONICA",
            257
        ],
        [
            "CHANDLER",
            87
        ],
        [
            "JOEY",
            234
        ],
        [
            "PHOEBE",
            183
        ]
    ]
}, {
    "name": "ross",
    "counts": [
        [
            "RACHEL",
            523
        ],
        [
            "ROSS",
            76
        ],
        [
            "MONICA",
            205
        ],
        [
            "CHANDLER",
            178
        ],
        [
            "JOEY",
            337
        ],
        [
            "PHOEBE",
            184
        ]
    ]
}, {
    "name": "monica, mon",
    "counts": [
        [
            "RACHEL",
            293
        ],
        [
            "ROSS",
            195
        ],
        [
            "MONICA",
            83
        ],
        [
            "CHANDLER",
            221
        ],
        [
            "JOEY",
            153
        ],
        [
            "PHOEBE",
            199
        ]
    ]
}, {
    "name": "chandler",
    "counts": [
        [
            "RACHEL",
            149
        ],
        [
            "ROSS",
            135
        ],
        [
            "MONICA",
            283
        ],
        [
            "CHANDLER",
            63
        ],
        [
            "JOEY",
            213
        ],
        [
            "PHOEBE",
            143
        ]
    ]
}, {
    "name": "joey, joe",
    "counts": [
        [
            "RACHEL",
            349
        ],
        [
            "ROSS",
            196
        ],
        [
            "MONICA",
            237
        ],
        [
            "CHANDLER",
            293
        ],
        [
            "JOEY",
            113
        ],
        [
            "PHOEBE",
            160
        ]
    ]
}, {
    "name": "phoebe, pheebs",
    "counts": [
        [
            "RACHEL",
            317
        ],
        [
            "ROSS",
            179
        ],
        [
            "MONICA",
            277
        ],
        [
            "CHANDLER",
            114
        ],
        [
            "JOEY",
            182
        ],
        [
            "PHOEBE",
            88
        ]
    ]
}]